calcleaner/__init__.py
calcleaner/__main__.py
calcleaner/about_dialog.py
calcleaner/account_edit_dialog.py
calcleaner/accounts.py
calcleaner/accounts_manage_dialog.py
calcleaner/application.py
calcleaner/caldav_helpers.py
calcleaner/calendar_store.py
calcleaner/data_helpers.py
calcleaner/helpers.py
calcleaner/main_window.py
calcleaner/translation.py
calcleaner/data/images/calcleaner.svg
calcleaner/data/images/calcleaner_128.png
calcleaner/data/images/calcleaner_256.png
calcleaner/data/images/calcleaner_32.png
calcleaner/data/images/calcleaner_64.png
calcleaner/data/locales/de/LC_MESSAGES/org.flozz.calcleaner.mo
calcleaner/data/locales/fr/LC_MESSAGES/org.flozz.calcleaner.mo
calcleaner/data/locales/hr/LC_MESSAGES/org.flozz.calcleaner.mo
calcleaner/data/locales/it/LC_MESSAGES/org.flozz.calcleaner.mo
calcleaner/data/locales/nl/LC_MESSAGES/org.flozz.calcleaner.mo
calcleaner/data/locales/pt_BR/LC_MESSAGES/org.flozz.calcleaner.mo
calcleaner/data/locales/tr/LC_MESSAGES/org.flozz.calcleaner.mo
calcleaner/data/style/calcleaner.css
calcleaner/data/ui/account-edit-dialog.glade
calcleaner/data/ui/accounts-manage-dialog.glade
calcleaner/data/ui/main-window.glade
calcleaner-1.1.3.dist-info/COPYING
calcleaner-1.1.3.dist-info/METADATA
calcleaner-1.1.3.dist-info/WHEEL
calcleaner-1.1.3.dist-info/entry_points.txt
calcleaner-1.1.3.dist-info/top_level.txt
calcleaner-1.1.3.dist-info/RECORD
