Metadata-Version: 2.1
Name: calcleaner
Version: 1.1.3
Summary: A simple graphical tool to purge old events from CalDAV calendars
Home-page: https://calcleaner.flozz.org/
Author: Fabien LOISON
License: GPLv3
Project-URL: Source Code, https://github.com/flozz/calcleaner
Project-URL: Changelog, https://github.com/flozz/calcleaner#changelog
Project-URL: Issues, https://github.com/flozz/calcleaner/issues
Project-URL: Chat, https://discord.gg/P77sWhuSs4
Project-URL: Donate, https://github.com/flozz/calcleaner#supporting-this-project
Keywords: calendar caldav event cleaner purge prune
License-File: COPYING
Requires-Dist: caldav (>=0.9.1)
Requires-Dist: PyGObject (>=3.26)
Provides-Extra: dev
Requires-Dist: nox ; extra == 'dev'
Requires-Dist: flake8 ; extra == 'dev'
Requires-Dist: black ; extra == 'dev'
Requires-Dist: pytest ; extra == 'dev'
